Metadata-Version: 1.0
Name: shiny-probability
Version: 1.2
Summary: Gaussian distributions
Home-page: UNKNOWN
Author: Shinibali
Author-email: UNKNOWN
License: UNKNOWN
Platform: UNKNOWN
